rag_pipeline_ops/__init__.py
rag_pipeline_ops/rag_pipeline_ops.py
rag_pipeline_ops-0.1.5.dist-info/METADATA
rag_pipeline_ops-0.1.5.dist-info/WHEEL
rag_pipeline_ops-0.1.5.dist-info/top_level.txt
rag_pipeline_ops-0.1.5.dist-info/RECORD
