Metadata-Version: 2.1
Name: rag_pipeline_ops
Version: 0.1.5
Summary: A package for RAG Pipeline Operations
Author: faith6
Author-email: root39293@gmail.com
Classifier: Programming Language :: Python :: 3.12
Requires-Dist: numpy
Requires-Dist: hnswlib
Requires-Dist: openai
Requires-Dist: pytest
Requires-Dist: chromadb
